tdstone/__init__.py
tdstone/code.py
tdstone/data_distribution.py
tdstone/data_modeling.py
tdstone/dataset_generation.py
tdstone/feature_store.py
tdstone/model.py
tdstone/prepared_dataset.py
tdstone/scoring_results.py
tdstone/sto_framework.py
tdstone/trained_model.py
tdstone/utils.py
tdstone/data/feature_engineering.py
tdstone/data/feature_engineering_jsonoutput.py
tdstone/data/feature_engineering_reducer.py
tdstone/data/scoring.py
tdstone/data/training.py
tdstone/mapper/__init__.py
tdstone/mapper/feature.py
tdstone/mapper/scoring.py
tdstone/mapper/training.py
tdstone-0.3.5.dist-info/METADATA
tdstone-0.3.5.dist-info/WHEEL
tdstone-0.3.5.dist-info/top_level.txt
tdstone-0.3.5.dist-info/RECORD
