Metadata-Version: 2.1
Name: tdstone
Version: 0.3.5
Summary: A package for Script Table Operator that applies set theory to machine learning in Python.
Author: Denis Molin
License: UNKNOWN
Platform: UNKNOWN
Requires-Python: >=3.6
Requires-Dist: teradataml (>=17.10)
Requires-Dist: pandas
Requires-Dist: numpy
